TurboTalk_Custom/__init__.py
TurboTalk_Custom-0.2.5.dist-info/METADATA
TurboTalk_Custom-0.2.5.dist-info/WHEEL
TurboTalk_Custom-0.2.5.dist-info/top_level.txt
TurboTalk_Custom-0.2.5.dist-info/RECORD
