Metadata-Version: 2.1
Name: TurboTalk_Custom
Version: 0.2.5
Requires-Dist: opyngpt
